LICENSE
MANIFEST.in
Makefile
README.md
requirements.txt
setup.cfg
setup.py
test-requirements.txt
tox.ini
kubeshift/__init__.py
kubeshift/api.py
kubeshift/base.py
kubeshift/client.py
kubeshift/config.py
kubeshift/constants.py
kubeshift/exceptions.py
kubeshift/kubernetes.py
kubeshift/openshift.py
kubeshift/utils.py
kubeshift.egg-info/PKG-INFO
kubeshift.egg-info/SOURCES.txt
kubeshift.egg-info/dependency_links.txt
kubeshift.egg-info/requires.txt
kubeshift.egg-info/top_level.txt