Metadata-Version: 1.0
Name: kubeshift
Version: 0.0.4
Summary: A universal python library for container orchestrators
Home-page: https://github.com/cdrage/kubeshift
Author: cdrage
Author-email: cdrage@redhat.com
License: LGPL3
Keywords: kubernetes,kubeshift,openshift,docker
Platform: UNKNOWN
